private_assistant_picture_display_skill/__init__.py
private_assistant_picture_display_skill/config.py
private_assistant_picture_display_skill/immich/__init__.py
private_assistant_picture_display_skill/immich/client.py
private_assistant_picture_display_skill/immich/config.py
private_assistant_picture_display_skill/immich/models.py
private_assistant_picture_display_skill/immich/payloads.py
private_assistant_picture_display_skill/immich/storage.py
private_assistant_picture_display_skill/immich/sync_service.py
private_assistant_picture_display_skill/main.py
private_assistant_picture_display_skill/models/__init__.py
private_assistant_picture_display_skill/models/commands.py
private_assistant_picture_display_skill/models/device.py
private_assistant_picture_display_skill/models/image.py
private_assistant_picture_display_skill/models/immich_sync_job.py
private_assistant_picture_display_skill/picture_skill.py
private_assistant_picture_display_skill/py.typed
private_assistant_picture_display_skill/services/__init__.py
private_assistant_picture_display_skill/services/device_mqtt_client.py
private_assistant_picture_display_skill/services/image_manager.py
private_assistant_picture_display_skill/templates/describe_image.j2
private_assistant_picture_display_skill/templates/next_picture.j2
private_assistant_picture_display_skill/utils/__init__.py
private_assistant_picture_display_skill/utils/color_analysis.py
private_assistant_picture_display_skill/utils/image_processing.py
private_assistant_picture_display_skill/utils/metadata_builder.py
private_assistant_picture_display_skill-0.6.0.dist-info/licenses/LICENSE
private_assistant_picture_display_skill-0.6.0.dist-info/WHEEL
private_assistant_picture_display_skill-0.6.0.dist-info/entry_points.txt
private_assistant_picture_display_skill-0.6.0.dist-info/METADATA
private_assistant_picture_display_skill-0.6.0.dist-info/RECORD
