Metadata-Version: 2.4
Name: private-assistant-picture-display-skill
Version: 0.6.0
Summary: Skill to dynamically display images from various sources via external agents.
Keywords: 
Author: stkr22
Author-email: stkr22 <stkr22@github.com>
License-Expression: GPL-3.0-only
License-File: LICENSE
Classifier: Development Status :: 4 - Beta
Classifier: Environment :: Console
Classifier: Programming Language :: Python
Classifier: Intended Audience :: Developers
Classifier: Operating System :: OS Independent
Classifier: Programming Language :: Python :: 3.12
Classifier: Programming Language :: Python :: 3.13
Requires-Dist: pydantic
Requires-Dist: jinja2~=3.1.3
Requires-Dist: private-assistant-commons~=6.3.0
Requires-Dist: typer~=0.21.1
Requires-Dist: httpx~=0.28.0
Requires-Dist: minio~=7.2.0
Requires-Dist: pyyaml~=6.0.0
Requires-Dist: pillow~=12.1.0
Requires-Dist: pillow-heif~=1.1.1
Requires-Dist: coloraide~=6.2.1
Requires-Python: >=3.12, <3.14
Project-URL: Homepage, https://github.com/stkr22/private-assistant-picture-display-skill-py
Project-URL: Repository, https://github.com/stkr22/private-assistant-picture-display-skill-py
Project-URL: Documentation, https://github.com/stkr22/private-assistant-picture-display-skill-py/tree/main/docs
Project-URL: Issues, https://github.com/stkr22/private-assistant-picture-display-skill-py/issues
Project-URL: Changelog, https://github.com/stkr22/private-assistant-picture-display-skill-py/blob/main/CHANGELOG.md
